tokko_cli/__init__.py
tokko_cli/cli.py
tokko_cli/conf.py
tokko_cli/daemon.py
tokko_cli/exceptions.py
tokko_cli/helpers.py
tokko_cli/minions.py
tokko_cli/playbooks.py
tokko_cli/projects.py
tokko_cli/repos.py
tokko_cli/templates.py
tokko_cli/users.py
tokko_cli/utils.py
tokko_cli-0.0.2.8.dist-info/METADATA
tokko_cli-0.0.2.8.dist-info/WHEEL
tokko_cli-0.0.2.8.dist-info/entry_points.txt
tokko_cli-0.0.2.8.dist-info/top_level.txt
tokko_cli-0.0.2.8.dist-info/RECORD
