Metadata-Version: 2.1
Name: tokko-cli
Version: 0.0.2.8
Summary: Ned Flanders Industries
Home-page: https://github.com/TokkoLabs/services-tokkobroker/tree/development/tools/tokko-cli
Author: Jose Salgado
Author-email: jsalgado@navent.com
License: BSD License
Platform: UNKNOWN
Classifier: Intended Audience :: Developers
Classifier: License :: Free To Use But Restricted
Classifier: Operating System :: POSIX :: Linux
Classifier: Programming Language :: Python
Classifier: Programming Language :: Python :: 3.8
Classifier: Topic :: Internet :: WWW/HTTP
Classifier: Topic :: Software Development
Requires-Dist: tokko-rpc (==0.0.2)
Requires-Dist: click (==7.1.2)
Requires-Dist: arrow (==0.15.6)
Requires-Dist: pyaml (==20.4.0)
Requires-Dist: jinja2 (==2.11.2)
Requires-Dist: distro (==1.5.0)
Requires-Dist: GitPython (==3.1.7)
Requires-Dist: requests (==2.24.0)
Requires-Dist: coloredlogs (==14.0)
